LICENSE
MANIFEST.in
README.md
setup.py
pytchfork/__init__.py
pytchfork/pytchfork.py
pytchfork.egg-info/PKG-INFO
pytchfork.egg-info/SOURCES.txt
pytchfork.egg-info/dependency_links.txt
pytchfork.egg-info/pbr.json
pytchfork.egg-info/requires.txt
pytchfork.egg-info/top_level.txt
pytchfork.egg-info/zip-safe
tests/__init__.py
tests/sample_program.py
tests/test_context_manager.py
tests/test_decorator.py
tests/unit_tests.py