Metadata-Version: 1.0
Name: pytchfork
Version: 0.0.2
Summary: multiprocessing decorator with queue management & redis features
Home-page: https://github.com/shaunvxc/pytchfork
Author: Shaun Viguerie
Author-email: shaunvig114@gmail
License: MIT
Platform: UNKNOWN
